wordinserter/__init__.py
wordinserter/cli.py
wordinserter/exceptions.py
wordinserter/operations.py
wordinserter/utils.py
wordinserter/images/404.png
wordinserter/parsers/__init__.py
wordinserter/parsers/html.py
wordinserter/parsers/markdown.py
wordinserter/parsers/fixes/__init__.py
wordinserter/parsers/fixes/list_elements.py
wordinserter/parsers/fixes/table_colspans.py
wordinserter/parsers/fixes/whitespace.py
wordinserter/renderers/__init__.py
wordinserter/renderers/com.py
wordinserter-1.1.3.dist-info/LICENSE.md
wordinserter-1.1.3.dist-info/METADATA
wordinserter-1.1.3.dist-info/WHEEL
wordinserter-1.1.3.dist-info/entry_points.txt
wordinserter-1.1.3.dist-info/top_level.txt
wordinserter-1.1.3.dist-info/RECORD
