Metadata-Version: 2.1
Name: wordinserter
Version: 1.1.3
Summary: Render HTML and Markdown to a specific portion of a word document
Home-page: https://github.com/orf/wordinserter
Author: Tom
Author-email: tom@tomforb.es
License: MIT
Platform: UNKNOWN
Classifier: Programming Language :: Python :: 3 :: Only
Classifier: Programming Language :: Python :: 3.4
Classifier: Programming Language :: Python :: 3.5
Classifier: Programming Language :: Python :: 3.6
Requires-Dist: BeautifulSoup4
Requires-Dist: cssutils
Requires-Dist: requests
Requires-Dist: webcolors
Requires-Dist: pygments
Requires-Dist: lxml
Requires-Dist: contexttimer
Requires-Dist: docopt
